Metadata-Version: 2.1
Name: odoo-addon-partner_contact_age_range
Version: 18.0.1.0.0.2
Requires-Python: >=3.10
Requires-Dist: odoo-addon-partner_contact_birthdate==18.0.*
Requires-Dist: odoo==18.0.*
Summary: Age Range for Contact's
Home-page: https://github.com/OCA/partner-contact
License: AGPL-3
Author: Druidoo, Odoo Community Association (OCA)
Author-email: support@odoo-community.org
Classifier: Programming Language :: Python
Classifier: Framework :: Odoo
Classifier: Framework :: Odoo :: 18.0
Classifier: License :: OSI Approved :: GNU Affero General Public License v3
